.gitignore
.travis.yml
LICENSE
MANIFEST.in
README.rst
setup.cgf
setup.py
tox.ini
docs/FLOPS.txt
docs/Stempel_Status.pptx
docs/Stencil_Blueprints.pptx
docs/Summary-DK.docx
docs/Usage.md
docs/classes.png
docs/malas.pdf
docs/packages.png
stempel/__init__.py
stempel/analysis.py
stempel/analysis.py_old
stempel/benchkernel.py
stempel/fix_yaml.py
stempel/lextab.py
stempel/likwid_bench_auto.py
stempel/pycparser_utils.py
stempel/stempel.py
stempel/utilities.py
stempel/yacctab.py
stempel.egg-info/PKG-INFO
stempel.egg-info/SOURCES.txt
stempel.egg-info/dependency_links.txt
stempel.egg-info/entry_points.txt
stempel.egg-info/requires.txt
stempel.egg-info/top_level.txt
stempel/examples/machine-files/AMD_Opteron_Processor_6274.yml
stempel/examples/machine-files/BroadwellEP_E5-2697_CoD.yml
stempel/examples/machine-files/HaswellEX_E5-2695v3.yml
stempel/examples/machine-files/HaswellEX_E5-2695v3_CoD.yml
stempel/examples/machine-files/Intel_Xeon_CPU_E5-2640_v4_mod.yml
stempel/examples/machine-files/Intel_Xeon_CPU_E5-2640_v4_mod2.yml
stempel/examples/machine-files/Intel_Xeon_CPU_X5650_2.67GHz.yml
stempel/examples/machine-files/Intel_Xeon_CPU_X5650_2.67GHz_mod.yml
stempel/examples/machine-files/IvyBridgeEP-E5-2690v2.yaml
stempel/examples/machine-files/IvyBridgeEP_E5-2660v2.yml
stempel/examples/machine-files/SandyBridgeEP_E5-2680.yml
stempel/examples/test-runs/2d-2r-isotropic-constant-star-stencil-1224-Intel_Xeon_CPU_X5650_2.txt
stempel/examples/test-runs/2d-2r-isotropic-constant-star-stencil-2448-Intel_Xeon_CPU_X5650_2.txt
stempel/examples/test-runs/2d-2r-isotropic-constant-star-stencil-306-Intel_Xeon_CPU_X5650_2.txt
stempel/examples/test-runs/2d-2r-isotropic-constant-star-stencil-612-Intel_Xeon_CPU_X5650_2.txt
stempel/examples/test-runs/2d-2r-star-constant-lima.pdf
stempel/examples/test-runs/2d-2r-star-constant-lima.png
stempel/headers/Makefile
stempel/headers/dummy.c
stempel/headers/kerncraft.h
stempel/headers/timing.c
stempel/headers/timing.h
stempel/stencils/__init__.py
stempel/stencils/boxstencil.py
stempel/stencils/starstencil.py
tests/testfiles/HaswellEX_E5-2695v3.yml