Metadata-Version: 1.2
Name: stempel
Version: 0.1.0
Summary: Stencil TEMPlate Engineering Library
Home-page: https://github.com/RRZE-HPC/stempel
Author: Danilo Guerrera
Author-email: danilo.guerrera@unibas.ch
License: AGPLv3
Keywords: hpc performance benchmark analysis stencil
Platform: UNKNOWN
Classifier: Development Status :: 3 - Alpha
Classifier: Intended Audience :: Developers
Classifier: Intended Audience :: Science/Research
Classifier: Topic :: Scientific/Engineering
Classifier: Topic :: Software Development
Classifier: Topic :: Utilities
Classifier: License :: OSI Approved :: GNU Affero General Public License v3
Classifier: Programming Language :: Python :: 3
Classifier: Programming Language :: Python :: 3.4
Requires-Python: >=3.4
